hil_uds_server_gui/__init__.py
hil_uds_server_gui/__main__.py
hil_uds_server_gui/client.py
hil_uds_server_gui/config.yaml
hil_uds_server_gui/default.qss
hil_uds_server_gui/main.py
hil_uds_server_gui/ui/__init__.py
hil_uds_server_gui/ui/card.py
hil_uds_server_gui/ui/home.py
hil_uds_server_gui/ui/window.py
hil_uds_server_gui-0.0.1.dist-info/METADATA
hil_uds_server_gui-0.0.1.dist-info/WHEEL
hil_uds_server_gui-0.0.1.dist-info/top_level.txt
hil_uds_server_gui-0.0.1.dist-info/RECORD
